photos_picker-1.0.0.dist-info/METADATA
photos_picker-1.0.0.dist-info/RECORD
photos_picker-1.0.0.dist-info/WHEEL
photos_picker-1.0.0.dist-info/top_level.txt
photospicker/__init__.py
photospicker/photos_picker.py
photospicker/event/__init__.py
photospicker/event/end_filter_event.py
photospicker/event/end_upload_event.py
photospicker/event/scan_progress_event.py
photospicker/event/start_filter_event.py
photospicker/event/start_upload_event.py
photospicker/exception/__init__.py
photospicker/exception/abstract_exception.py
photospicker/exception/picker_exception.py
photospicker/exception/uploader_exception.py
photospicker/filter/__init__.py
photospicker/filter/abstract_filter.py
photospicker/filter/resize_filter.py
photospicker/filter/rotate_filter.py
photospicker/filter/filters/__init__.py
photospicker/filter/filters/resize_filter.py
photospicker/filter/filters/rotate_filter.py
photospicker/picker/__init__.py
photospicker/picker/abstract_exif_date_picker.py
photospicker/picker/abstract_picker.py
photospicker/picker/last_photos_picker.py
photospicker/picker/picker_photo.py
photospicker/picker/random_picker.py
photospicker/picker/pickers/__init__.py
photospicker/picker/pickers/last_photos_picker.py
photospicker/picker/pickers/random_picker.py
photospicker/picker/pickers/smart_picker.py
photospicker/uploader/__init__.py
photospicker/uploader/abstract_uploader.py
photospicker/uploader/dropbox_uploader.py
photospicker/uploader/filesystem_uploader.py
photospicker/uploader/gdrive_uploader.py
photospicker/uploader/uploaders/__init__.py
photospicker/uploader/uploaders/dropbox_uploader.py
photospicker/uploader/uploaders/filesystem_uploader.py
photospicker/uploader/uploaders/gdrive_uploader.py
tests/__init__.py
tests/test_photos_picker.py
tests/filter/__init__.py
tests/filter/test_resize_filter.py
tests/filter/test_rotate_filter.py
tests/filter/filters/__init__.py
tests/filter/filters/test_resize_filter.py
tests/filter/filters/test_rotate_filter.py
tests/functional/__init__.py
tests/functional/test_functional.py
tests/picker/__init__.py
tests/picker/picker_photo_stub.py
