Metadata-Version: 2.1
Name: photos-picker
Version: 1.0.0
Summary: Pick photos following a given strategy and upload them to various destinations
Home-page: https://github.com/l-vo/photos-picker
Author: Laurent VOULLEMIER
Author-email: laurent.voullemier@gmail.com
License: MIT
Keywords: photos upload photoframe
Platform: UNKNOWN
Classifier: Intended Audience :: Developers
Classifier: License :: OSI Approved :: MIT License
Classifier: Operating System :: OS Independent
Classifier: Programming Language :: Python
Classifier: Programming Language :: Python :: 2
Requires-Dist: Pillow
Requires-Dist: zope.event
Requires-Dist: dropbox
Requires-Dist: pydrive
